[{"id":"6c1389c4.483a98","type":"tab","label":"Flow 1","disabled":false,"info":""},{"id":"5ab290df.d4c3c","type":"rpi-gpio out","z":"6c1389c4.483a98","name":"","pin":"15","set":true,"level":"0","freq":"","out":"out","x":273.5,"y":137,"wires":[]},{"id":"1418bb2f.3ff065","type":"ui_switch","z":"6c1389c4.483a98","tab":"a87885b9.50c928","name":"RUN","topic":"","group":"System","order":1,"onvalue":"1","offvalue":"0","x":86.5,"y":136,"wires":[["5ab290df.d4c3c"]]},{"id":"5276e2ee.fb45dc","type":"ui_switch","z":"6c1389c4.483a98","tab":"a87885b9.50c928","name":"OP1","topic":"","group":"Outputs","order":"2","onvalue":"1","offvalue":"0","x":91.5,"y":176,"wires":[["46fbd8f.8b29528"]]},{"id":"44bd1a68.c6c604","type":"ui_switch","z":"6c1389c4.483a98","tab":"a87885b9.50c928","name":"OP2","topic":"","group":"Outputs","order":"3","onvalue":"1","offvalue":"0","x":88.5,"y":216,"wires":[["635743df.0f9ddc"]]},{"id":"e03633ee.1b4a","type":"ui_switch","z":"6c1389c4.483a98","tab":"a87885b9.50c928","name":"OP3","topic":"","group":"Outputs","order":"4","onvalue":"1","offvalue":"0","x":87.5,"y":255,"wires":[["2829645e.29f3dc"]]},{"id":"7ebd55fd.cdedec","type":"ui_switch","z":"6c1389c4.483a98","tab":"a87885b9.50c928","name":"OP5","topic":"","group":"Outputs","order":"6","onvalue":"1","offvalue":"0","x":84,"y":329,"wires":[["63c5078f.d687f8"]]},{"id":"3d3ad447.45db5c","type":"ui_switch","z":"6c1389c4.483a98","tab":"a87885b9.50c928","name":"OP4","topic":"","group":"Outputs","order":"5","onvalue":"1","offvalue":"0","x":88,"y":292,"wires":[["6dc23519.750cdc"]]},{"id":"61eb218a.03da7","type":"ui_switch","z":"6c1389c4.483a98","tab":"a87885b9.50c928","name":"OP7","topic":"","group":"Outputs","order":"8","onvalue":"1","offvalue":"0","x":81,"y":400,"wires":[["c94f4816.7f6468"]]},{"id":"e4ac4606.ae4db8","type":"ui_switch","z":"6c1389c4.483a98","tab":"a87885b9.50c928","name":"OP6","topic":"","group":"Outputs","order":"7","onvalue":"1","offvalue":"0","x":81,"y":366,"wires":[["a1ae775f.b0d728"]]},{"id":"212a3749.b8fa78","type":"ui_switch","z":"6c1389c4.483a98","tab":"a87885b9.50c928","name":"OP8","topic":"","group":"Outputs","order":"9","onvalue":"1","offvalue":"0","x":79,"y":435,"wires":[["a20d8ff5.d6134"]]},{"id":"7f011b75.8f10c4","type":"ui_switch","z":"6c1389c4.483a98","tab":"a87885b9.50c928","name":"OP9","topic":"","group":"Outputs","order":"10","onvalue":"1","offvalue":"0","x":77,"y":470,"wires":[["a3f28920.5fd758"]]},{"id":"d6c4b712.08a388","type":"ui_switch","z":"6c1389c4.483a98","tab":"a87885b9.50c928","name":"OP10","topic":"","group":"Outputs","order":"11","onvalue":"1","offvalue":"0","x":78,"y":505,"wires":[["9f93233d.38b75"]]},{"id":"c5f3b018.c286","type":"ui_switch","z":"6c1389c4.483a98","tab":"a87885b9.50c928","name":"OP11","topic":"","group":"Outputs","order":"12","onvalue":"1","offvalue":"0","x":78,"y":542,"wires":[["92a1935d.edad1"]]},{"id":"f20fb229.0216f","type":"ui_switch","z":"6c1389c4.483a98","tab":"a87885b9.50c928","name":"OP12","topic":"","group":"Outputs","order":"13","onvalue":"1","offvalue":"0","x":75,"y":577,"wires":[["f78271f5.6a0be"]]},{"id":"46fbd8f.8b29528","type":"rpi-gpio out","z":"6c1389c4.483a98","name":"","pin":"11","set":true,"level":"0","freq":"","out":"out","x":271,"y":176,"wires":[]},{"id":"635743df.0f9ddc","type":"rpi-gpio out","z":"6c1389c4.483a98","name":"","pin":"10","set":true,"level":"0","freq":"","out":"out","x":270,"y":214,"wires":[]},{"id":"2829645e.29f3dc","type":"rpi-gpio out","z":"6c1389c4.483a98","name":"","pin":"8","set":true,"level":"0","freq":"","out":"out","x":269,"y":254,"wires":[]},{"id":"6dc23519.750cdc","type":"rpi-gpio out","z":"6c1389c4.483a98","name":"","pin":"7","set":true,"level":"0","freq":"","out":"out","x":266,"y":292,"wires":[]},{"id":"63c5078f.d687f8","type":"rpi-gpio out","z":"6c1389c4.483a98","name":"","pin":"5","set":true,"level":"0","freq":"","out":"out","x":265,"y":329,"wires":[]},{"id":"a1ae775f.b0d728","type":"rpi-gpio out","z":"6c1389c4.483a98","name":"","pin":"3","set":true,"level":"0","freq":"","out":"out","x":265,"y":369,"wires":[]},{"id":"c94f4816.7f6468","type":"rpi-gpio out","z":"6c1389c4.483a98","name":"","pin":"12","set":true,"level":"0","freq":"","out":"out","x":265,"y":402,"wires":[]},{"id":"a20d8ff5.d6134","type":"rpi-gpio out","z":"6c1389c4.483a98","name":"","pin":"13","set":true,"level":"0","freq":"","out":"out","x":264,"y":438,"wires":[]},{"id":"a3f28920.5fd758","type":"rpi-gpio out","z":"6c1389c4.483a98","name":"","pin":"18","set":true,"level":"0","freq":"","out":"out","x":264,"y":473,"wires":[]},{"id":"9f93233d.38b75","type":"rpi-gpio out","z":"6c1389c4.483a98","name":"","pin":"19","set":true,"level":"0","freq":"","out":"out","x":263,"y":507,"wires":[]},{"id":"92a1935d.edad1","type":"rpi-gpio out","z":"6c1389c4.483a98","name":"","pin":"21","set":true,"level":"0","freq":"","out":"out","x":263,"y":543,"wires":[]},{"id":"f78271f5.6a0be","type":"rpi-gpio out","z":"6c1389c4.483a98","name":"","pin":"22","set":true,"level":"0","freq":"","out":"out","x":263,"y":581,"wires":[]},{"id":"ea308879.014628","type":"ui_switch","z":"6c1389c4.483a98","tab":"a87885b9.50c928","name":"Enable","topic":"","group":"System","order":1,"onvalue":"1","offvalue":"0","x":97,"y":100,"wires":[["7db332e7.9f372c"]]},{"id":"7db332e7.9f372c","type":"rpi-gpio out","z":"6c1389c4.483a98","name":"","pin":"16","set":true,"level":"0","freq":"","out":"out","x":272,"y":100,"wires":[]},{"id":"8f3abc66.1fa4e","type":"rpi-gpio in","z":"6c1389c4.483a98","name":"","pin":"23","intype":"down","debounce":"25","read":true,"x":514.5,"y":99,"wires":[["dcfe54a2.b8ecb8"]]},{"id":"311c5beb.1f6714","type":"rpi-gpio in","z":"6c1389c4.483a98","name":"","pin":"24","intype":"down","debounce":"25","read":true,"x":512,"y":143,"wires":[["67223e44.e61a3"]]},{"id":"dcfe54a2.b8ecb8","type":"ui_text","z":"6c1389c4.483a98","tab":"a87885b9.50c928","name":"IP1","group":"Inputs","order":1,"format":"{{msg.payload}}","x":672.5,"y":101,"wires":[]},{"id":"67223e44.e61a3","type":"ui_text","z":"6c1389c4.483a98","tab":"a87885b9.50c928","name":"IP2","group":"Inputs","order":"2","format":"{{msg.payload}}","x":672,"y":145,"wires":[]},{"id":"ddfba7e2.f95b08","type":"rpi-gpio in","z":"6c1389c4.483a98","name":"","pin":"26","intype":"down","debounce":"25","read":true,"x":511,"y":189,"wires":[["3891300f.c951e"]]},{"id":"e2ea79d1.3d7f88","type":"rpi-gpio in","z":"6c1389c4.483a98","name":"","pin":"29","intype":"down","debounce":"25","read":true,"x":508.5,"y":233,"wires":[["5b50bd02.fbe314"]]},{"id":"3891300f.c951e","type":"ui_text","z":"6c1389c4.483a98","tab":"a87885b9.50c928","name":"IP3","group":"Inputs","order":"3","format":"{{msg.payload}}","x":669,"y":191,"wires":[]},{"id":"5b50bd02.fbe314","type":"ui_text","z":"6c1389c4.483a98","tab":"a87885b9.50c928","name":"IP4","group":"Inputs","order":"4","format":"{{msg.payload}}","x":668.5,"y":235,"wires":[]},{"id":"a9b6a234.cdb8a","type":"rpi-gpio in","z":"6c1389c4.483a98","name":"","pin":"31","intype":"down","debounce":"25","read":true,"x":510,"y":275,"wires":[["8e7638c7.eefff8"]]},{"id":"447e5720.7ae598","type":"rpi-gpio in","z":"6c1389c4.483a98","name":"","pin":"32","intype":"down","debounce":"25","read":true,"x":507.5,"y":319,"wires":[["a284f8d1.775f58"]]},{"id":"8e7638c7.eefff8","type":"ui_text","z":"6c1389c4.483a98","tab":"a87885b9.50c928","name":"IP5","group":"Inputs","order":"5","format":"{{msg.payload}}","x":668,"y":277,"wires":[]},{"id":"a284f8d1.775f58","type":"ui_text","z":"6c1389c4.483a98","tab":"a87885b9.50c928","name":"IP6","group":"Inputs","order":"6","format":"{{msg.payload}}","x":667.5,"y":321,"wires":[]},{"id":"ec31d181.99ddb","type":"rpi-gpio in","z":"6c1389c4.483a98","name":"","pin":"33","intype":"down","debounce":"25","read":true,"x":508,"y":360,"wires":[["edb5b732.1eed08"]]},{"id":"98820dac.d5852","type":"rpi-gpio in","z":"6c1389c4.483a98","name":"","pin":"35","intype":"down","debounce":"25","read":true,"x":505.5,"y":404,"wires":[["be2cab96.782aa8"]]},{"id":"edb5b732.1eed08","type":"ui_text","z":"6c1389c4.483a98","tab":"a87885b9.50c928","name":"IP6","group":"Inputs","order":"7","format":"{{msg.payload}}","x":666,"y":362,"wires":[]},{"id":"be2cab96.782aa8","type":"ui_text","z":"6c1389c4.483a98","tab":"a87885b9.50c928","name":"IP8","group":"Inputs","order":"8","format":"{{msg.payload}}","x":665.5,"y":406,"wires":[]},{"id":"c8670b38.3415d8","type":"rpi-gpio in","z":"6c1389c4.483a98","name":"","pin":"36","intype":"down","debounce":"25","read":true,"x":504,"y":445,"wires":[["876f46fe.3d77c8"]]},{"id":"31ea4290.11c82e","type":"rpi-gpio in","z":"6c1389c4.483a98","name":"","pin":"37","intype":"down","debounce":"25","read":true,"x":501.5,"y":489,"wires":[["34a25905.1969c6"]]},{"id":"876f46fe.3d77c8","type":"ui_text","z":"6c1389c4.483a98","tab":"a87885b9.50c928","name":"IP9","group":"Inputs","order":"9","format":"{{msg.payload}}","x":662,"y":447,"wires":[]},{"id":"34a25905.1969c6","type":"ui_text","z":"6c1389c4.483a98","tab":"a87885b9.50c928","name":"IP10","group":"Inputs","order":"10","format":"{{msg.payload}}","x":661.5,"y":491,"wires":[]},{"id":"a7b4bc29.4c3fb","type":"rpi-gpio in","z":"6c1389c4.483a98","name":"","pin":"38","intype":"down","debounce":"25","read":true,"x":500,"y":535,"wires":[["f90cd93e.b5d878"]]},{"id":"c1ef24a6.312128","type":"rpi-gpio in","z":"6c1389c4.483a98","name":"","pin":"40","intype":"down","debounce":"25","read":true,"x":497.5,"y":579,"wires":[["9e41f54d.a5e738"]]},{"id":"f90cd93e.b5d878","type":"ui_text","z":"6c1389c4.483a98","tab":"a87885b9.50c928","name":"IP11","group":"Inputs","order":"11","format":"{{msg.payload}}","x":658,"y":537,"wires":[]},{"id":"9e41f54d.a5e738","type":"ui_text","z":"6c1389c4.483a98","tab":"a87885b9.50c928","name":"IP12","group":"Inputs","order":"12","format":"{{msg.payload}}","x":657.5,"y":581,"wires":[]},{"id":"a87885b9.50c928","type":"ui_tab","z":"","name":"Home","icon":"dashboard","order":"1"}]


